LICENSE.txt
MANIFEST.in
README.rst
__init__.py
editor.py
editor_gtk.py
editor_html.py
editor_qt.py
field.py
field_gtk.py
field_html.py
field_qt.py
html_server.py
html_utils.py
introsp.py
observe.py
setup.cfg
setup.py
undoredo.py
./LICENSE.txt
./README.rst
./__init__.py
./editor.py
./editor_gtk.py
./editor_html.py
./editor_qt.py
./field.py
./field_gtk.py
./field_html.py
./field_qt.py
./html_server.py
./html_utils.py
./introsp.py
./observe.py
./undoredo.py
./icons/add.svg
./icons/down.svg
./icons/python.svg
./icons/remove.svg
./icons/up.svg
./js/jquery-1.11.0.min.js
./js/w2ui-1.3.2.css
./js/w2ui-1.3.2.js
Editobj3.egg-info/PKG-INFO
Editobj3.egg-info/SOURCES.txt
Editobj3.egg-info/dependency_links.txt
Editobj3.egg-info/top_level.txt
doc/conf.py
doc/index.rst
doc/doctrees/environment.pickle
doc/doctrees/index.doctree
doc/examples/calculator.py
doc/examples/config.py
doc/examples/dialog.png
doc/examples/directory.png
doc/examples/downloader.py
doc/examples/file.png
doc/examples/file_manager.py
doc/examples/help_browser.py
doc/examples/html_multiuser.py
doc/examples/jiba.png
doc/examples/login.py
doc/html/.buildinfo
doc/html/genindex.html
doc/html/index.html
doc/html/objects.inv
doc/html/py-modindex.html
doc/html/search.html
doc/html/searchindex.js
doc/html/_images/editobj3_gtk.png
doc/html/_images/editobj3_html.png
doc/html/_sources/index.rst.txt
doc/html/_static/_sphinx_javascript_frameworks_compat.js
doc/html/_static/basic.css
doc/html/_static/dialog-note.png
doc/html/_static/dialog-seealso.png
doc/html/_static/dialog-todo.png
doc/html/_static/dialog-topic.png
doc/html/_static/dialog-warning.png
doc/html/_static/doctools.js
doc/html/_static/documentation_options.js
doc/html/_static/epub.css
doc/html/_static/file.png
doc/html/_static/footerbg.png
doc/html/_static/headerbg.png
doc/html/_static/ie6.css
doc/html/_static/jquery-3.6.0.js
doc/html/_static/jquery.js
doc/html/_static/language_data.js
doc/html/_static/middlebg.png
doc/html/_static/minus.png
doc/html/_static/plus.png
doc/html/_static/pygments.css
doc/html/_static/pyramid.css
doc/html/_static/searchtools.js
doc/html/_static/transparent.gif
