Metadata-Version: 2.1
Name: Editobj3
Version: 0.2
Summary: An automatic dialog box generator for Python objects, supporting multiple graphical backends: Qt, GTK and HTML (single-user or with multiple users).
Home-page: https://bitbucket.org/jibalamy/editobj3
Author: Lamy Jean-Baptiste (Jiba)
Author-email: jibalamy@free.fr
License: LGPLv3+
Platform: UNKNOWN
Classifier: Development Status :: 4 - Beta
Classifier: Intended Audience :: Developers
Classifier: Programming Language :: Python :: 3
Classifier: License :: OSI Approved :: GNU Lesser General Public License v3 or later (LGPLv3+)
Classifier: Operating System :: OS Independent
Classifier: Environment :: Web Environment
Classifier: Environment :: X11 Applications :: Qt
Classifier: Environment :: X11 Applications :: GTK
Classifier: Topic :: Internet :: WWW/HTTP :: HTTP Servers
Classifier: Topic :: Scientific/Engineering :: Human Machine Interfaces
Classifier: Topic :: Software Development :: User Interfaces
Classifier: Topic :: Software Development :: Libraries :: Python Modules
License-File: LICENSE.txt
